ploudos/__init__.py
ploudos/ploudos.py
PloudOS-1.0.1.dist-info/LICENSE
PloudOS-1.0.1.dist-info/METADATA
PloudOS-1.0.1.dist-info/WHEEL
PloudOS-1.0.1.dist-info/top_level.txt
PloudOS-1.0.1.dist-info/RECORD
