Metadata-Version: 2.1
Name: PloudOS
Version: 1.0.1
Summary: Unofficial API for PloudOS
Home-page: https://github.com/mytja/PloudOS-API
Author: mytja
License: UNKNOWN
Platform: UNKNOWN
Classifier: Programming Language :: Python :: 3
Classifier: License :: OSI Approved :: MIT License
Classifier: Operating System :: OS Independent
Requires-Python: >=3
License-File: LICENSE
Requires-Dist: httpx
